<?xml version="1.0"?>
<opencv_storage>
<opencv_ml_ann_mlp>
  <format>3</format>
  <layer_sizes>
    256 6 1</layer_sizes>
  <activation_function>SIGMOID_SYM</activation_function>
  <f_param1>6.6666666666666663e-001</f_param1>
  <f_param2>1.7159000000000000e+000</f_param2>
  <min_val>-9.4999999999999996e-001</min_val>
  <max_val>9.4999999999999996e-001</max_val>
  <min_val1>-9.7999999999999998e-001</min_val1>
  <max_val1>9.7999999999999998e-001</max_val1>
  <training_params>
    <train_method>BACKPROP</train_method>
    <dw_scale>1.0000000000000000e-003</dw_scale>
    <moment_scale>0.</moment_scale>
    <term_criteria>
      <epsilon>1.0000000000000000e-004</epsilon>
      <iterations>300</iterations></term_criteria></training_params>
  <input_scale>
    3.0159826244973448e+001 -1.7516867915528092e+000
    5.4440262477648298e+002 -6.3109817080098560e+000
    4.5953256743200171e+002 -3.1838791700316165e+000
    6.3481082259781363e+002 -7.7612399562894945e+000
    8.2105934326403781e+002 -5.1971980736059242e+000
    3.7676025117153472e+003 -3.8853160610142647e+000
    7.1145996877830680e+002 -7.1051944339304569e+000
    3.6143143409086036e+002 -6.8325585825581152e+000
    4.2327805408711515e+002 -2.8676345542684945e+000
    3.6074426574888444e+003 -3.8888094760848051e+000
    3.4099992489182273e+003 -2.4976779741762591e+000
    3.9353524800502496e+003 -3.3604221541686101e+000
    7.7899045964523964e+002 -7.5342961565197308e+000
    3.3908443141809703e+003 -4.1837529896981733e+000
    2.8092497983462960e+002 -6.5444895459331152e+000
    1.7175101664473038e+002 -6.0672080836633242e+000
    5.9044092143760167e+002 -6.7983551597376417e+000
    5.9261254533854271e+003 -4.4457247034796321e+000
    3.8639999668082496e+003 -3.9182786395242850e+000
    7.7486073662460931e+003 -4.5096041354736958e+000
    4.5359585230665352e+003 -4.3266696287485127e+000
    2.0091884396840953e+004 -1.2092747971779469e+000
    3.7123766558534580e+003 -4.5365822825614268e+000
    6.8637919874045019e+003 -3.7807180190215210e+000
    8.2099482063814617e+002 -9.4922259837779084e+000
    7.4451077367153066e+003 -4.2609545607443797e+000
    4.4872190075356120e+003 -3.5109524329894288e+000
    7.2836695054598868e+003 -3.6558083139353381e+000
    3.3126095475063266e+002 -6.0580277611613838e+000
    6.9059187317996739e+003 -3.8224780093464106e+000
    1.4278652295113420e+002 -4.9926865429548961e+000
    5.9074751918565710e+002 -6.5768066513807684e+000
    3.8320781133540083e+002 -3.1289078542178688e+000
    3.7463926402478446e+003 -4.1895914188695080e+000
    3.1929737222945814e+003 -2.4348042176811351e+000
    5.0329924725885276e+003 -4.6249675882919714e+000
    4.8353765840381775e+003 -3.4351686633096583e+000
    1.5172631125827516e+004 -1.3534907618406489e+000
    4.4100419496943296e+003 -3.5477321749157915e+000
    4.2748243489478982e+003 -4.3279822933671399e+000
    2.5356976455033905e+003 -2.7566374468563906e+000
    1.0101144153462763e+004 -1.8130231275688828e+000
    1.2308739429047009e+004 -1.2104614867274968e+000
    1.6618796080409822e+004 -1.7414879694510843e+000
    4.2734939219509024e+003 -4.4805018588006797e+000
    1.1516669123120813e+004 -1.7143242442794433e+000
    3.6431467892726196e+003 -4.3443046328138895e+000
    3.4217855558725787e+003 -5.4502608420124350e+000
    5.2149136997188134e+002 -7.3992329590922417e+000
    6.2808137721183639e+003 -4.1076440441515096e+000
    4.8053927768570720e+003 -4.0026433411950464e+000
    6.7230337530441120e+003 -3.4755750590848922e+000
    5.6040344223998027e+003 -5.1617612416480547e+000
    2.6649056841376419e+004 -1.3031954165371160e+000
    4.6261719168936861e+003 -3.7290596649812642e+000
    7.0460839330222589e+003 -3.1541266069626794e+000
    2.1772656911518948e+002 -5.0967762612464309e+000
    5.7629719567340144e+003 -3.3354045524315024e+000
    4.7431119068322396e+003 -3.9176311301172735e+000
    6.8109929689228111e+003 -3.5100665176548311e+000
    1.7838776294932981e+002 -4.4047166186148958e+000
    6.6661959098367215e+003 -3.0628836242474136e+000
    4.5652173750136495e+002 -6.1653470664735650e+000
    1.1462814279063143e+003 -5.4823601593684561e+000
    8.4426897075685338e+002 -6.1952499351549388e+000
    4.0628969195281575e+003 -4.4256376379647122e+000
    5.4596739086326825e+003 -3.8053358050504285e+000
    4.6929209380589145e+003 -4.2872465908742461e+000
    6.5419500451032900e+003 -2.8827526778722659e+000
    2.2500161780081882e+004 -1.4509525002200228e+000
    7.4817245208201566e+003 -3.4858373515294394e+000
    5.5014593999542576e+003 -2.8351942992933257e+000
    5.0989929044642340e+003 -3.5402442740027000e+000
    2.1735103085819279e+004 -1.6585797438507872e+000
    2.2099913510314036e+004 -1.4845228797616987e+000
    2.0479947994929760e+004 -1.3206763594884356e+000
    8.5145822837382184e+003 -3.8343669602378130e+000
    1.8423453054072765e+004 -1.0890555323574282e+000
    7.4241031731568710e+003 -3.5188349047123788e+000
    6.0861184804872782e+003 -3.0285705693683203e+000
    3.5533308119143676e+003 -3.7827393537386151e+000
    2.1693708483807146e+004 -1.0492104747271873e+000
    2.0888769712740952e+004 -1.5266450672275864e+000
    2.3845423791806985e+004 -1.0123214635106776e+000
    2.3698012894111107e+004 -1.2734979195199856e+000
    6.9543601893840911e+004 -4.8583281028875830e-001
    2.2622869740754759e+004 -1.2643500864076818e+000
    3.6452430108521767e+004 -1.0186292385897333e+000
    4.8843322875871227e+003 -4.4726106558134786e+000
    2.1339912656431927e+004 -1.1353091563927262e+000
    2.1206467391629310e+004 -1.1396057645963793e+000
    3.7905756665951834e+004 -1.1407211812173947e+000
    7.4342864398926022e+003 -3.5276566009553325e+000
    3.0210994954717848e+004 -7.9551324842097015e-001
    7.3173789332062897e+003 -3.1969246455789588e+000
    9.8517513268831790e+003 -2.3506215834493309e+000
    7.7297658759194724e+002 -9.1102621608495760e+000
    2.8443143715598085e+003 -4.1957175416870651e+000
    4.5391690588090150e+003 -3.6784427849813319e+000
    5.5547319470793691e+003 -4.7760557953415050e+000
    6.9988801596436952e+003 -4.0206157613665106e+000
    2.1755889445047695e+004 -1.3795745019576191e+000
    5.6010377773040636e+003 -3.3831489643838131e+000
    6.6572315471236043e+003 -4.0461555602350536e+000
    3.2882004801114113e+003 -4.1083510407688619e+000
    1.1849486893338448e+004 -1.8784855958913529e+000
    1.7044158488995748e+004 -1.4105308629860756e+000
    1.8497942936826614e+004 -1.5507234063507112e+000
    5.1915369721111738e+003 -4.2545349788528517e+000
    1.4962239766547889e+004 -1.8412739150393378e+000
    5.2834224821349771e+003 -4.7642396380915324e+000
    3.8035712209015260e+003 -3.4584238267859098e+000
    2.8066092676724537e+002 -6.9031795568558527e+000
    6.0195848111945070e+003 -3.6391953407952351e+000
    3.8265008103554665e+003 -3.8309013203383859e+000
    6.4743681662313602e+003 -3.0547678792916906e+000
    5.4688142907511537e+003 -3.0476019297455430e+000
    2.6103356896402533e+004 -1.0099855633882380e+000
    4.8696928697566127e+003 -2.9309330777951903e+000
    8.6126929496080102e+003 -2.6381539089482153e+000
    1.1286497533953948e+002 -4.0960755988281576e+000
    6.3432675347791137e+003 -3.3269720616215395e+000
    4.3909952545248052e+003 -4.5399841339397229e+000
    7.3279242645334461e+003 -3.2566627754629831e+000
    4.6872250664328982e+002 -5.4092279220079087e+000
    7.0397281556930138e+003 -2.1941695855198424e+000
    1.1265177655204800e+003 -7.1161808673939042e+000
    2.1257935377022836e+003 -4.9921637706255391e+000
    4.2361749054730535e+002 -3.5487747986275719e+000
    3.9320939934727767e+002 -5.9135873826313814e+000
    2.0825622790474567e+003 -2.4721795800212356e+000
    2.0444286496210643e+002 -5.2755940195401072e+000
    5.1862112515399540e+003 -3.7345760522056617e+000
    4.5011646573965190e+003 -4.1314173438375201e+000
    4.1302096939964904e+003 -4.3324964550043301e+000
    2.0404519937793663e+002 -5.2176342092259986e+000
    3.4297035916021559e+003 -2.5231690127211719e+000
    4.8433300055250493e+003 -4.1461607958977948e+000
    1.5392154871487764e+004 -1.4309743064747580e+000
    4.8601501508330020e+003 -4.2415248477613261e+000
    5.1828711271285929e+003 -3.9661278067087400e+000
    4.0979359927721634e+003 -3.5102640930146549e+000
    4.0970419175255593e+003 -4.7160258382278988e+000
    5.4406422786239057e+002 -7.6347222165625768e+000
    3.8402301864468741e+003 -4.4286695679335919e+000
    5.6358654605805787e+003 -3.6858486810479976e+000
    1.1262436831041274e+004 -1.9548849305202307e+000
    8.0129132283026474e+003 -4.6462031199489990e+000
    1.7236096711942570e+004 -1.5283019767219310e+000
    2.6831265298594102e+004 -1.1534996014569450e+000
    1.3581834023132958e+004 -2.1020217962219210e+000
    6.4466463848272160e+003 -3.1490825130522802e+000
    5.6464932708123606e+003 -4.8428164148095121e+000
    5.4653694556396031e+003 -3.0633043057087943e+000
    1.6010989239747631e+004 -1.6175671675714041e+000
    5.2771723059066780e+003 -2.9039393362349104e+000
    4.1822255027622668e+003 -3.9308236278343740e+000
    6.4592170429492326e+003 -2.9712551741334328e+000
    3.2435510239563719e+003 -5.1959984031062332e+000
    1.0145020393362986e+003 -4.9600397304577051e+000
    2.7847264714717430e+003 -2.5335285580577360e+000
    3.8420142317655800e+003 -3.8113336149331012e+000
    1.3984709897878969e+004 -1.4579462057370289e+000
    4.6297786048807611e+003 -4.7296460592209808e+000
    1.7340549816771047e+004 -1.2393695245324139e+000
    1.8653421677595161e+004 -1.3231794506116317e+000
    1.4941004398459123e+004 -1.4853808835657294e+000
    4.0412439297561109e+003 -4.1088709119198503e+000
    1.0321876266274183e+004 -1.2036623906126453e+000
    1.4771521409254350e+004 -1.4129654382017325e+000
    6.2166968039924861e+004 -5.0111482858579570e-001
    1.7243495131269392e+004 -1.6957534013367881e+000
    1.3598505526808902e+004 -1.3372991858458425e+000
    1.4558420049077795e+004 -1.4473457244983066e+000
    1.6468432141901787e+004 -1.8673297582551303e+000
    4.1446085426463214e+003 -4.0112851431612047e+000
    3.7254025537083539e+003 -3.6776353569767695e+000
    6.6661959098367333e+003 -3.9083111509402739e+000
    1.5138451697384999e+004 -1.7816068862929795e+000
    5.6765731379393792e+003 -3.2579453728524195e+000
    1.6117534812704042e+004 -1.5503792822982847e+000
    2.2839945727448987e+004 -1.2273865954847050e+000
    1.5784743823708377e+004 -1.6031924188283657e+000
    6.4932598084719275e+003 -3.0078512466748517e+000
    5.1051681505559027e+003 -5.1851122018973186e+000
    6.3080362061408705e+003 -3.8034117334840785e+000
    1.7261290280619254e+004 -1.6325715810657095e+000
    3.9568949336978148e+003 -2.4984961908179160e+000
    4.6268011876552973e+003 -4.8011957192611474e+000
    5.7614248628470568e+003 -2.7803056834189168e+000
    5.4530128408598239e+003 -5.0783354410635049e+000
    1.1403617397036974e+003 -4.3417897540780261e+000
    8.9252147830147362e+002 -1.0600748915741883e+001
    2.9910554401211408e+002 -7.5309222668998030e+000
    2.8280155629929309e+003 -3.5045107715618213e+000
    1.3364816263011198e+002 -5.2997171113495209e+000
    7.1234079793190467e+003 -3.9428599522466401e+000
    5.9727681547023303e+003 -3.4728755878136353e+000
    4.2873545445452155e+003 -3.5365848582276831e+000
    4.3059992465693693e+002 -5.4917769228602982e+000
    3.7604106502666064e+003 -3.0332085533003097e+000
    4.8349524032155014e+003 -4.8690932558003199e+000
    1.4372253394174335e+004 -1.2666453174807351e+000
    3.7374806192622855e+003 -4.2479130627793902e+000
    6.6709917348526151e+003 -4.0079151113532747e+000
    6.2858999272600049e+003 -3.7664190557754491e+000
    5.6561358449900963e+003 -5.0364977182507005e+000
    1.0478735676380643e+003 -6.9989255224579727e+000
    3.4749120508364849e+003 -5.0773759858377394e+000
    5.1476514929053901e+003 -3.2863353940618047e+000
    1.0630188477379897e+004 -1.9879548524794695e+000
    5.0370838999547495e+003 -2.9802507919835195e+000
    2.3455803913404015e+004 -1.6638361729135234e+000
    2.4388078883609403e+004 -9.5672420031348426e-001
    1.0701315303229589e+004 -1.4606870712172288e+000
    6.5659328179004324e+003 -2.2687869530194509e+000
    5.1242560615425873e+003 -4.3453436455340464e+000
    8.8406138227127431e+003 -4.2567362129837498e+000
    1.5180707044496941e+004 -1.3297374867150045e+000
    6.5837438867731425e+003 -3.0497658802448173e+000
    6.5847328915783446e+003 -3.9348597568681636e+000
    7.8814629152616744e+003 -2.7360602886639409e+000
    4.2429471035326515e+003 -3.9172120317730457e+000
    1.9609762579604733e+003 -4.7399972231544094e+000
    2.6250649932882516e+002 -6.1434809806253252e+000
    1.6338155749649292e+002 -6.1080853035363170e+000
    3.8456222676015127e+003 -5.1767912666188787e+000
    4.6625940516152190e+002 -8.3033492332710530e+000
    6.0067132576887288e+003 -3.6636929579459934e+000
    5.6808037092563163e+003 -3.1993177405437518e+000
    4.4429779724788050e+003 -4.1329250537572451e+000
    8.1483760793767635e+002 -5.8846998711016738e+000
    3.8875377668492979e+003 -5.2561960422291234e+000
    3.1857782337834774e+003 -5.4869357552673126e+000
    1.2362403239748079e+004 -1.7206358917078735e+000
    4.9723988506006845e+003 -5.2613594510128419e+000
    4.6144085946712667e+003 -4.3271084675364353e+000
    4.6492742273472468e+003 -4.6196425827140963e+000
    3.0345503854368103e+003 -5.2101654723179696e+000
    9.2739057958044839e+002 -7.4705162386393456e+000
    1.7037397462061156e+002 -6.4299269913401904e+000
    6.1629625005721914e+002 -6.8628972248166846e+000
    3.7908745353403347e+003 -6.2846468516064729e+000
    1.2173138411358168e+003 -6.5593359611968021e+000
    6.8395482405786406e+003 -3.7857414495321948e+000
    9.0379875424207075e+003 -2.2050269387735635e+000
    4.4319006659086645e+003 -4.5965673528000393e+000
    1.7893480556390452e+003 -4.4261089443077024e+000
    5.1067787972883764e+002 -8.7960659756691886e+000
    1.2952694381580779e+003 -6.8192957500267450e+000
    4.5494673300282102e+003 -4.6549368798486901e+000
    1.3275273451849885e+003 -5.4760163951515795e+000
    1.0288791966298006e+003 -7.2098840229566319e+000
    1.8775237673567635e+003 -4.8308759566665813e+000
    1.0035856560463432e+003 -7.8491587274877892e+000
    3.9037644506629363e+002 -6.1325809783531477e+000</input_scale>
  <output_scale>
    1.0526315789473684e+000 0.</output_scale>
  <inv_output_scale>
    9.4999999999999996e-001 0.</inv_output_scale>
  <weights>
    <_>
      -3.0899965478919759e-003 3.3423399081960194e-003
      -3.4193451004272991e-003 1.0990176643241371e-002
      1.4161240024030851e-002 -2.2943563777026631e-002
      3.6732099653279796e-002 2.6159719850101570e-002
      -1.5111413088928495e-002 3.1107049460712771e-002
      3.7322239593924389e-002 -6.3980195377109528e-002
      -7.4690399092650732e-003 4.4788546771176328e-004
      7.9784075422274932e-004 2.8921230354621644e-004
      -7.0005983131054394e-003 -1.7556711724553272e-003
      -7.1342518259238557e-003 7.3678817666303830e-003
      4.1516263689374700e-004 -6.2646877591279407e-003
      5.4383977085533082e-003 1.0192892819635114e-003
      -1.9447942289470223e-003 7.7936141232267013e-003
      -2.4972015794054773e-003 2.7725732369310889e-003
      8.1694057664694498e-003 -1.7041445222813534e-002
      1.8037495523826111e-003 4.6146005417811112e-003
      -6.7527157466666411e-003 1.1771383471694626e-002
      3.7295538366717207e-003 -1.3985550069897304e-002
      -1.4565705709428349e-002 -1.6383660837390849e-002
      7.1044487133656679e-003 -1.9044371424228317e-002
      -1.6415929534426457e-002 3.6987352791097036e-002
      -1.6937033299739456e-002 -1.4147684496914864e-002
      1.4049433444130448e-003 -1.0485203476071762e-002
      -1.9012053227491613e-002 3.1693294757608882e-002
      -8.6670871452061791e-003 -9.8079836367924653e-003
      1.0119529215259767e-002 2.5060864396392875e-003
      -5.9218743932451532e-003 -9.2731298588240758e-003
      2.5108674714961511e-002 1.2919619172613991e-002
      -1.1642736152746568e-002 1.5751505145079212e-002
      2.4978952383860355e-002 -3.8411724039430752e-002
      -9.3856948867994359e-003 -2.0235250356608808e-002
      1.7474964468534058e-002 -1.8398447908294202e-002
      -9.0761799797663550e-003 6.7865985633325564e-003
      -1.2280093315869990e-002 -1.5898203703441763e-002
      3.2532440699367775e-003 -1.5581190095965154e-002
      -2.2045590061534059e-002 2.0770398344619391e-002
      -1.6535820099693736e-002 -7.2435605653728644e-003
      -1.5934633252723756e-004 -1.2699092580893218e-002
      -1.3544912161363191e-002 2.1426497403995291e-002
      -2.2868271486615466e-002 -1.4876221908578003e-002
      8.1949114184182176e-003 -1.4052713063327239e-002
      -1.4835382052661918e-002 3.3672409826749995e-002
      6.2387460332052132e-004 7.2618629846214634e-003
      -7.2408039697820920e-004 8.0451065424247820e-003
      5.5460880903682747e-003 2.2981904690673057e-003
      2.8248730778530275e-002 2.8127482014009900e-002
      -2.3192463502711147e-002 2.8247753277934159e-002
      3.9834667277290826e-002 -4.6458839968996773e-002
      9.3205426677280719e-003 4.0634357056585340e-003
      -1.3286025409232669e-002 1.2364908142759026e-002
      1.2031053284701800e-002 -4.0008033645259088e-002
      -2.2386352970844289e-002 -1.5696838986501000e-002
      1.5193084405442070e-002 -2.6462755560527032e-002
      -2.0900802284372386e-002 2.5431372834659616e-002
      -1.0222188768885991e-002 -7.8316543147298745e-003
      1.2600232623721992e-002 -6.6642029536859090e-003
      -1.1569623615262929e-003 1.1037003080874647e-002
      -1.8580786139706040e-002 -8.8825420904100026e-003
      1.4197819956851458e-002 -1.5218782624685344e-002
      -1.4108471312577500e-002 1.9586831997978157e-002
      1.0104657281748097e-002 9.8461016415457830e-003
      1.9567607729570411e-004 6.6725644303081292e-003
      1.2145551994976755e-002 -1.1421646644332990e-002
      2.2439719999712861e-002 2.0237218267346296e-002
      -1.8688161510568582e-002 2.9541711106970809e-002
      2.8213218309219669e-002 -4.1565372265424824e-002
      -1.7841471387884781e-002 -1.1893137535414112e-002
      1.5488793702200927e-002 -1.7561754797797632e-002
      -2.2809138068211110e-002 2.3615104777219450e-002
      -5.5676487315923660e-004 -3.4390987736943084e-004
      -1.1051516555270651e-002 9.1789556876189539e-003
      7.2792758499081603e-003 -7.9063230091915900e-003
      -4.0598410715602766e-002 -3.6967459998152728e-002
      2.8205816157961423e-002 -3.7946075248989790e-002
      -4.5186806956914800e-002 7.4050197668399639e-002
      2.4721470708272943e-002 1.9525151618696376e-002
      -1.4795260334551924e-002 2.9439505634134555e-002
      3.0900225846607732e-002 -5.2608233819267554e-002
      -1.9297237024528954e-002 -1.4701839926935861e-002
      3.3684771769361727e-003 -1.8073332035744415e-002
      -8.6217129516153006e-003 1.6742910234568444e-002
      1.4693070630036139e-002 1.2180578524684243e-002
      -1.3323935968349422e-002 2.0501771853700133e-002
      2.7676963653537487e-002 -2.9463901313865750e-002
      -1.9765929119738446e-002 -1.9158405344987417e-002
      1.2689427455700781e-002 -1.9445489381382422e-002
      -2.6829236414060070e-002 5.0094615697077190e-002
      -1.0470770899137758e-002 -3.0740971225518350e-003
      -3.2243987073952937e-003 -2.5639078981401927e-003
      -9.4475053962442745e-004 6.1719903822097892e-004
      1.0504981775714370e-002 9.1783991737849468e-003
      -1.0097066807492984e-002 1.0703435770335883e-002
      2.1672867751745380e-002 -2.4693319543454592e-002
      -8.2280968328818753e-003 -4.7668627065702287e-003
      4.7826203601700305e-003 -6.2173262910602562e-003
      -1.5402175981307381e-002 3.3648904452438025e-002
      6.6686276822226836e-003 6.3486299533235318e-003
      -4.4412919898977809e-003 6.4766906262086511e-003
      1.4553948979858069e-002 -2.2561061741365282e-002
      3.3104735031688870e-002 2.2794357437845986e-002
      -2.2105305432124044e-002 3.0877765332850107e-002
      3.7675696112583507e-002 -5.3344228209651408e-002
      -1.9337105457062416e-002 -1.3355904770126851e-002
      1.0589768154292360e-002 -2.2700009977590040e-002
      -2.0791563432737144e-002 1.7771749300039972e-002
      -3.3814679379366643e-002 -2.1031791872759470e-002
      1.5218875568580766e-002 -2.0145278596180722e-002
      -3.2858176891097532e-002 4.5894466630881772e-002
      -1.1380301220168610e-003 -5.8389169914472715e-004
      6.7436978138047613e-003 -2.5400647172926986e-003
      1.5687934495873077e-003 -1.9231719200278384e-003
      -8.7499374026343019e-003 -1.4611609277161696e-002
      9.2005997157978397e-003 -1.6184783090497319e-002
      -2.2082516050400253e-002 1.5879713502146127e-002
      -1.9381388129692822e-003 8.5832357989870374e-004
      4.6944514005200393e-004 -2.3066041114488392e-003
      1.9277978910506809e-003 2.8262047990839295e-004
      -1.8208273547275132e-002 -2.0083701205120218e-002
      1.2576874796159898e-002 -1.4981789009617962e-002
      -3.4598387733853049e-002 3.7721385915052266e-002
      1.5340136356276329e-002 1.9564325128376726e-002
      -1.8090446343153248e-002 2.2827951027514389e-002
      2.1290372712108398e-002 -4.5491062002086712e-002
      1.3873427557671120e-002 8.1556683470572627e-003
      -9.7140817700459015e-003 1.3664670141643088e-002
      2.3326204299673626e-002 -2.9531600472123960e-002
      -9.1492820280229519e-003 -1.3064978963642296e-002
      9.7591839602491487e-003 -1.4616102247302682e-002
      -1.2153073573877099e-002 2.3986476739996931e-003
      1.4123714289071840e-002 6.8391556126195978e-003
      9.0456336885020390e-004 9.1177863067285550e-003
      6.9789355247403245e-003 -1.4549465371132154e-002
      -7.8440897538104570e-003 -1.6512330391398762e-003
      -8.9561154187991847e-004 -6.1098347946414349e-003
      5.8117362224452416e-003 -8.1893075754661850e-003
      2.3107995878956712e-002 1.5925415028041578e-002
      -1.6612144925841083e-002 2.0689112897199789e-002
      1.7659585802692491e-002 -3.1994968293341704e-002
      1.0175047356152780e-002 1.5587035940817036e-002
      -8.1596349934058635e-003 1.5711502727903070e-002
      2.1791269647653065e-002 -3.2327663847684623e-002
      -2.6578290080191656e-002 -2.1065717653294531e-002
      1.1202088663468513e-002 -2.6799571705759927e-002
      -3.1488908373365064e-002 4.6325866478700857e-002
      8.9164529185156698e-003 8.9009620886168473e-004
      -2.9983440788981298e-003 -2.1775116023847784e-003
      8.7597412901718776e-003 -2.9399162495500736e-003
      2.3694532718400777e-002 1.9978929540861719e-002
      -1.0489019915262673e-002 1.1404983648769157e-002
      2.1475597411480855e-002 -3.9991573961968806e-002
      8.8224896683553634e-003 1.3889812845738937e-002
      -9.3661101940905971e-004 1.3918721153245031e-002
      9.9439625080819296e-003 -2.3929767010571566e-002
      1.0373772496420401e-002 4.2072254939659699e-003
      1.6386279603966868e-003 -4.1155257560443595e-004
      7.2012784569247777e-003 -1.5054654177439218e-002
      -1.8771143787231475e-002 -9.4889537357272565e-003
      1.6550995620611707e-002 -1.4017749424724493e-002
      -2.7667610875699238e-002 2.8624112604231262e-002
      -1.3836260896618652e-002 -7.5192090247362814e-003
      8.3420230638097913e-003 -1.0625355470951699e-002
      -1.5732757643844981e-002 2.6629312568605592e-002
      7.5224063974425230e-003 1.6830987658765180e-002
      -1.4932331778521026e-002 7.3164635040719505e-003
      1.9989572970546134e-002 -2.0755201639526460e-002
      1.2654324354226991e-002 1.9721809454221827e-002
      -5.7061768091165978e-003 1.8092332535503880e-002
      2.0502954180133402e-002 -1.9499119718582810e-002
      -4.5055487166987998e-002 -3.2412070519692547e-002
      2.0800967907483859e-002 -4.2877154865842461e-002
      -4.8377209030030274e-002 7.6170892594730796e-002
      5.8201246170608593e-003 2.4814901525159359e-003
      -1.6239407494870236e-003 5.7995043369350316e-003
      1.3268593993143948e-002 -1.7333660442921488e-002
      5.3267033801402824e-003 7.5199783824937295e-003
      -3.7296480861138061e-005 4.2628014603458770e-003
      -3.4779750871678995e-003 2.0425471119324785e-003
      1.0203884537358288e-002 1.1619908452960808e-002
      1.5016603267379381e-003 9.4114213283433730e-003
      1.1385971807812879e-002 -1.0604788819356118e-002
      -3.7492179684179248e-002 -3.9661800793097141e-002
      2.6559082862602633e-002 -3.7961351737792123e-002
      -4.8016674591092989e-002 7.3631965600787760e-002
      1.0969440477045655e-002 1.7642884204675059e-002
      -2.5592590203651704e-003 1.0345544726308147e-002
      1.8037477227379861e-002 -2.9001962793740545e-002
      -1.9052940647120972e-002 -1.0334702245839943e-002
      7.3776853469509941e-003 -2.1033799869334041e-002
      -1.4068928700131106e-002 4.3771629818942503e-002
      -4.3102931081915624e-002 -3.2743331022717863e-002
      2.2189664336794739e-002 -4.5780805014582093e-002
      -4.9736876478453811e-002 7.4350438022419918e-002
      -5.6728334324107977e-003 -1.3401765558215882e-003
      3.0251673877111089e-003 -4.2974285725015573e-003
      5.0024913636766864e-003 -2.7460334644651236e-003
      -9.2864881662698372e-003 -2.1173982962151167e-004
      9.2797962917416724e-003 -1.7429585199898613e-004
      -1.1117820185456127e-003 1.0411339136778757e-002
      7.4262629604989272e-003 1.7808506191292111e-003
      3.8685690598754215e-003 -2.4469322144803985e-003
      9.3314979008314921e-003 -4.3138564527954344e-003
      -2.2355893742555108e-003 -4.8410375338471924e-003
      -7.3365565740363377e-003 -7.7046007874403402e-004
      8.4830124723114589e-003 -9.9811597186847002e-003
      2.1999652693190853e-002 8.0554748278276345e-003
      -1.6594280859963652e-002 1.5504850856078733e-002
      1.6542947216094648e-002 -3.2180306449256575e-002
      -7.9015926044657438e-003 -1.5028555608530248e-003
      1.2184185772122613e-003 -9.1679738723670513e-003
      -5.3228730202377695e-003 -1.2934845877274627e-004
      -1.2410365604938259e-002 -4.8504213059311439e-003
      6.3672158830553015e-003 -1.1411583120305751e-002
      -1.5780848676292272e-002 1.1142787194222788e-002
      1.3464330087132736e-003 1.3781653947455977e-003
      6.5732115210440480e-004 5.0330679258135721e-003
      1.0205460802097673e-002 -7.6925958070753033e-003
      1.9698809371745314e-003 -2.7863935180207624e-003
      7.5700137405363514e-003 -5.7687513705859421e-003
      5.2439293402565847e-003 6.3787975133758302e-004
      -2.6683641436212775e-003 -2.5131059286346981e-003
      -2.5793217242601780e-004 5.6907825129634436e-003
      1.7020472223105794e-003 6.6768104567561087e-003
      1.2040671946570700e-002 6.5150836333045048e-003
      -1.2162780078831517e-003 1.2050334929441398e-002
      1.2943241211431804e-002 -3.3072912322579140e-002
      -3.9099651236507722e-002 -3.2974606604788737e-002
      1.7877427309429816e-002 -3.9184456349666386e-002
      -4.3232917524715753e-002 6.7710173406175134e-002
      -3.9892175904272719e-003 -2.9271086983734878e-003
      9.9383797688149898e-003 -3.6622513429472492e-003
      1.2179987608523564e-004 1.5980945604063069e-003
      -1.7425390547570759e-002 -7.2009575276892075e-003
      8.1426180259158796e-003 -6.3483593188073482e-003
      -1.3903390529021443e-002 2.4063937660528785e-002
      1.3024501744316918e-002 8.6948632022289789e-003
      -4.5220300703362288e-003 6.3882464332588474e-003
      1.8322821427472213e-002 -1.2243509670625659e-002
      -2.5485623238987353e-002 -1.5219101727834089e-002
      1.1111343207968916e-002 -2.1807833276046049e-002
      -3.4046131560767960e-002 4.7219004839022305e-002
      -4.5207124206341357e-003 5.4368590349166317e-003
      4.8948649752021556e-003 5.4471199418835940e-003
      -4.1306475641605051e-003 -1.3984985459598840e-002
      -2.0631712662390490e-002 -7.0223213753709815e-003
      5.2850572592369202e-003 -1.3662906265603547e-002
      -1.8984020427445937e-002 1.9739212382570547e-002
      2.1709174647007518e-002 1.2491080030281231e-002
      -9.5946631780932882e-003 1.7537625119520363e-002
      2.5692938560742135e-002 -3.2978404920590676e-002
      2.1398549025286517e-003 4.1085698915209841e-003
      -5.0480434694645951e-003 -1.7584154332402277e-003
      9.8567527977208684e-003 -1.2463664922834659e-002
      -2.3189153606846688e-002 -9.7729829928690903e-003
      8.5252925963648050e-003 -1.2443119097640445e-002
      -1.8339340521675945e-002 3.5404822021692137e-002
      -2.1380445328645151e-002 -7.5181497697198738e-003
      1.1875070318237764e-002 -1.3864505191003997e-002
      -1.4620521858331133e-002 3.2232067188767470e-002
      1.0193611252622622e-002 5.2859941158954421e-003
      -5.0180826468208739e-003 -2.4284369118423811e-003
      -4.0917795521040450e-003 -8.6162193946862989e-003
      4.5215733524027218e-002 3.6824833425241434e-002
      -3.3923070289590587e-002 4.1437364647952404e-002
      5.4543256889395056e-002 -6.3334422215594030e-002
      4.6773674210259802e-004 4.5404442586217059e-003
      1.3797165971248871e-003 -2.3773168322362460e-003
      7.3331858037164761e-004 -4.7656732284886254e-003
      1.9728443124682252e-002 2.4985745584688020e-002
      -7.1848470311698274e-003 2.0852366400546687e-002
      2.4171241480631322e-002 -4.5216707292227175e-002
      9.9197250444360598e-003 5.6156264241319226e-003
      -6.6144174764840085e-003 1.8426438798987033e-002
      2.0075241939204177e-002 -3.1965547243546145e-002
      5.5286432113413201e-003 4.7958274127225557e-003
      2.0286678025943929e-003 9.1525854673695367e-003
      3.8467609946997883e-004 -3.7247254456950350e-003
      -1.7898003503032802e-002 -1.6183740342333209e-002
      8.7340623575038832e-003 -8.9809931281775376e-003
      -1.9629188006419121e-002 2.4315129480344887e-002
      3.6137431334950300e-004 -4.2466783391549223e-003
      -2.2362087231261709e-003 9.3544334018994023e-004
      9.3247307648033160e-003 -6.7182038114691200e-003
      -2.1874294225533716e-002 -1.5690400816456725e-002
      5.4195909692156402e-003 -2.3175782929704070e-002
      -2.1884470313208920e-002 3.1919528250399530e-002
      -2.0515403400688192e-002 -7.5385221183349857e-003
      1.7754943684564217e-002 -1.8532877198122882e-002
      -1.9896509608272092e-002 2.9245255837774903e-002
      -1.0496515290364106e-003 6.5748224781886589e-003
      -7.4835774595981390e-003 3.8772175033157147e-003
      1.0514626301777109e-002 -1.5888620302615158e-002
      3.8055470697192471e-003 6.9656883732885809e-003
      -7.1430977624024842e-003 -2.6469151415537818e-003
      6.9089169435472102e-003 -4.1770179818034136e-003
      -1.5342400989523533e-002 -8.9002606419142250e-003
      1.7947794267726455e-002 -2.1329061907936375e-002
      -1.5040540374075503e-002 2.7916371107188694e-002
      -2.4595081314327326e-002 -2.5800577669921144e-002
      2.2356744146202409e-002 -1.8140924890293196e-002
      -2.3264958452909157e-002 4.9425639849779969e-002
      2.0195519493636422e-002 8.1079096668887057e-003
      -6.2339407110035246e-003 8.6087428970854779e-003
      1.5655707431251824e-002 -2.2969559309166360e-002
      2.5635175315361785e-002 1.3176868499922835e-002
      -1.7987091180323760e-002 1.2401338362786349e-002
      1.7695351145438916e-002 -3.0806783150669037e-002
      1.2263298816245459e-002 5.1159073646029375e-003
      -4.0797450705831123e-003 9.0820869461763400e-003
      1.5488056432256196e-002 -1.2807441682475870e-002
      -2.0995244058359093e-003 -3.4646680257859747e-004
      3.1473193301871285e-003 -4.6671946094089265e-003
      -7.7679238283709330e-004 4.0924998056612594e-003
      2.1499115671421213e-002 2.2450906193963640e-002
      -1.2216079023969591e-002 1.9288045714062209e-002
      3.5582029231009622e-002 -4.6934842498120279e-002
      3.9884810639048487e-003 4.8995398094112538e-003
      -2.7549737595983226e-003 1.8064333130554951e-002
      1.5596849254703834e-002 -2.6910456976909070e-002
      4.2812546529766753e-003 2.1285244386637744e-004
      -2.0972483578328717e-003 1.1594458649970398e-003
      1.0245017437493087e-002 -2.7678142475742674e-002
      -1.9601096493045918e-002 -1.2336560950832264e-002
      5.8674743988901355e-003 -2.6283045761823626e-002
      -2.4881640193921067e-002 3.7695918688559676e-002
      2.3919202253125611e-002 1.1330671484705235e-002
      -1.8086976473493499e-002 2.6115328706277145e-002
      2.6830824224571212e-002 -3.6799678401583685e-002
      4.0934928158256799e-002 2.5611483452353721e-002
      -2.3943399711950059e-002 3.7360334219787711e-002
      4.1396053269790192e-002 -5.7040784640613282e-002
      2.7498124455889165e-002 1.6845249860936048e-002
      -1.8468278235051927e-002 2.0845567470603146e-002
      1.8709660686980843e-002 -3.1181768068171765e-002
      1.2503988081401388e-002 8.5144453011241749e-003
      -7.4642373630578263e-003 1.2202100984063500e-002
      5.4791736968352878e-003 -1.0481610915249330e-002
      -1.3974676761156119e-002 -1.4500221129979382e-002
      1.8433870107846534e-004 -1.4337013200472218e-002
      -1.9375669452448070e-002 2.9569581546899378e-002
      2.1388755623538043e-002 1.3624692188115666e-002
      -1.1437644265161567e-002 2.2234085188786310e-002
      2.4156014962660302e-002 -2.9686326787741406e-002
      -2.9799202511644318e-002 -1.9430752883115722e-002
      2.4352665737159874e-002 -3.5526191990939024e-002
      -3.0911312795073077e-002 5.2152287218929554e-002
      -3.3398269115605043e-003 -2.3217885231955828e-003
      6.6361650698594282e-004 5.4176994682794315e-003
      -6.7120847922279223e-003 -4.6446622188797701e-003
      1.4584289507211056e-002 1.4972331844198959e-002
      -7.0844153813554871e-005 1.5859169762532477e-002
      1.1236417374118922e-002 -1.1477143563046180e-002
      6.1833888428743560e-003 3.5490239446774566e-003
      4.8440536203195344e-004 -3.8507187572205150e-003
      -1.7661102771035094e-003 -9.4003601093273943e-003
      5.1611882407894376e-003 6.8764588533804915e-003
      -3.0085971434064200e-003 5.3645870875547843e-003
      6.5115550288812824e-003 -1.8809188415993383e-002
      3.1086108021668554e-003 -1.0889952346870896e-003
      -3.7241831635060741e-005 -3.8542597798743414e-003
      -9.0105221673515892e-003 8.7255349399032369e-003
      -1.7949521457616011e-002 -1.4827518635772403e-002
      1.8684170227263552e-002 -2.5500848331358815e-002
      -2.4673802855357311e-002 4.7654503574784353e-002
      3.7340159079016291e-002 2.5961766650516166e-002
      -1.9159695638312536e-002 4.0900087020304912e-002
      4.3943274687161214e-002 -6.5504495778434313e-002
      -1.2542111962351884e-002 -1.7810414222913806e-002
      1.4328072294453499e-002 -1.9228128587080520e-002
      -2.0250110377092914e-002 3.7229915328021425e-002
      -1.8222416749556072e-002 -1.5783815534748384e-002
      1.8187804720114366e-002 -2.9143683234310332e-002
      -2.3159704317845569e-002 5.1474342626022601e-002
      -3.8925071020301412e-002 -2.3914943774477736e-002
      2.1461813979280868e-002 -3.4783502252554110e-002
      -3.7279083921677121e-002 6.3267837348467595e-002
      1.8830125523202665e-002 2.4060310868085678e-002
      -7.6915698279496764e-003 2.0926724733496039e-002
      2.8944370264562692e-002 -3.1774972850666834e-002
      -2.6765166265266045e-002 -2.7012324845859009e-002
      6.7093967216114835e-003 -2.9177221973919230e-002
      -3.3197893421978132e-002 5.4820554585065635e-002
      -1.5291766917235534e-002 -1.6371293285130557e-002
      1.4567690143377741e-002 -2.0272588249928534e-002
      -1.2496377442419883e-002 2.7611279905568113e-002
      1.0763942038009932e-002 3.5660824954164331e-003
      -7.7362832223230532e-003 7.7418332879183767e-003
      1.6500937638051945e-002 -2.0997751069398406e-002
      1.4127996765961640e-002 1.4079680199841536e-002
      -2.6076489795665864e-003 8.1683552470728869e-003
      1.7380304077736431e-002 -1.5876397306004045e-002
      1.7926211327880231e-002 1.1474130845842088e-002
      -4.2857057015653127e-003 1.5839267196942172e-002
      2.7002482037322195e-002 -3.3472296261663585e-002
      -3.6974322270440593e-004 -3.2007521045267547e-003
      -6.5267426628149725e-003 7.5582213099530159e-004
      -9.4993175175331589e-003 1.5600093047011853e-002
      -5.5744091026734997e-003 -6.6194150331809355e-003
      1.4068648918509842e-002 -5.3532095430437361e-003
      -1.8415681314448928e-002 3.6477354726456700e-003
      -1.0465674925383604e-002 -3.6725582655433246e-003
      -1.1135317421611009e-003 -8.3906463795994229e-003
      -1.8998309890499387e-002 1.8817848555783591e-002
      -3.1286262239500146e-003 -4.1315933179662786e-003
      7.8383929061537176e-003 -7.3674986697036375e-004
      1.2935063616866334e-003 8.5915474752529149e-003
      -1.5347976012155813e-004 -1.1787874132970130e-002
      5.3395866628124025e-003 -7.2279553388714607e-003
      -1.6186583492889789e-002 2.5610044317008352e-002
      1.2131859375761103e-002 9.9434213323378595e-003
      2.4469538855097783e-003 9.2657976906977725e-003
      1.5476487271407985e-002 -2.0097798862322457e-002
      -1.4586621874145375e-002 -2.0884394130720109e-002
      1.5916996703974944e-002 -1.1991212429244580e-002
      -2.3753421965050363e-002 2.3374884407067715e-002
      2.4774398534470849e-002 1.8069535690019543e-002
      -1.4395518806040052e-002 1.6918410934290654e-002
      1.6430225127553381e-002 -3.3789683083387895e-002
      -2.6837671845578275e-002 -2.3145501814990154e-002
      6.6490041549767164e-003 -2.3427767957319687e-002
      -1.8624156480294668e-002 3.3460732968255705e-002
      -1.6678142039704132e-002 -1.0261491537444207e-002
      1.9436485791209945e-002 -1.9893244826549025e-002
      -2.3229156035917329e-002 2.2485327381422376e-002
      9.5352024994121258e-003 5.5991643762167481e-003
      9.8791766264465578e-004 6.6971890268142031e-004
      5.2629961437372407e-003 -1.0141047505453695e-002
      -1.9449806918300405e-002 -9.0003812803615864e-003
      4.6750889601601857e-003 -1.2592253406724799e-002
      -1.6330819916657375e-002 1.9878531663138434e-002
      -9.2491140697823927e-003 -4.7911650408314814e-003
      5.9736595373338129e-003 -7.4463761658524023e-003
      -2.3575678536390799e-002 2.8879621537916574e-002
      2.4816253075003257e-002 2.2735565566517891e-002
      -9.2558175480836734e-003 1.1114718587309148e-002
      2.4801267531749185e-002 -4.5713457784316729e-002
      5.8000031726440837e-003 1.4453068228547529e-002
      -1.2435870278831371e-002 1.5584614287843274e-002
      9.8891461549405393e-003 -2.0227706121891911e-002
      2.9775400082722635e-002 1.8841116914034773e-002
      -1.6261501947070475e-002 3.1635248623029424e-002
      3.7689201919273899e-002 -5.5315987837297909e-002
      3.7998767637586507e-002 2.3854115817140677e-002
      -1.6898126622849136e-002 3.4798903357120957e-002
      4.3185569959958273e-002 -5.2116482183564176e-002
      -8.8705033800197935e-003 -6.6009603320966162e-003
      1.1255645963609374e-002 -1.3360241845799065e-002
      -3.6066986045661317e-003 1.1979627700671777e-002
      2.8073456498106192e-002 1.6748156034406009e-002
      -9.3312847676128262e-003 1.8647823267264923e-002
      2.2202470245757916e-002 -3.3645504894445837e-002
      2.8118357438015853e-002 1.9218149721111681e-002
      -1.8613647724725964e-002 2.6643007229245827e-002
      1.9468481151149981e-002 -4.0055646673797539e-002
      -3.8815434420343326e-003 -9.4962535376629936e-003
      1.0342992202859750e-003 -1.1222821314363893e-002
      -1.3336396288103531e-002 1.1193002138089851e-002
      4.2596980013247758e-004 -1.7938590287274677e-003
      -2.7446065645537598e-003 3.1528532635333494e-003
      2.9075790515802700e-003 -6.8122004688924596e-003
      1.3039862534955848e-002 9.8125494227018790e-003
      3.4125251451233069e-004 7.6303541821431372e-003
      2.7505153661440073e-003 -3.1053799953991144e-003
      1.8173173688181790e-002 1.1692605974652959e-002
      -9.6857178922524108e-003 1.6835595782004446e-002
      1.5937448537406716e-002 -1.9843335477453254e-002
      -7.0904734404055843e-003 2.6108696273791027e-003
      -3.6320635649591815e-003 -7.4498750196868666e-003
      -7.0292276566521171e-003 1.7832205855324631e-002
      -3.5874409111589324e-002 -2.5179313596570461e-002
      1.6914656606073789e-002 -2.9630471984014705e-002
      -4.2380935692298262e-002 5.0314674242321104e-002
      -1.1896791231440745e-002 -1.1746740966124271e-002
      9.3313222770703772e-004 -1.1363150094262623e-002
      -8.0138568927172211e-003 2.1427507831240252e-002
      1.1147940243675738e-002 1.7613159463832225e-003
      -5.1977721055666108e-003 1.2988178499836352e-002
      1.2425982217357277e-002 -1.0067330198650597e-002
      -1.0180477018638097e-002 1.2244576915198903e-004
      4.7871097440047652e-003 -3.3039941944316724e-003
      -1.8204055569672382e-002 2.7869473621571335e-002
      3.4890632191557584e-003 -2.5478927695082639e-003
      -9.3305628905342095e-003 1.1624710965245188e-003
      1.9126546513572488e-002 -1.9607682347047243e-002
      1.9701995932237346e-002 1.3766809550002184e-002
      -4.4154313805596854e-003 1.0451292229238327e-002
      1.2261425169732934e-002 -2.7932752498551726e-002
      -1.1682751405639976e-002 -7.4695158227511818e-003
      8.4643591687298160e-003 -1.0447338578584738e-002
      3.0113611447610163e-003 -4.6363528604673665e-003
      2.5144519414083731e-003 -5.3001795947146537e-003
      5.8022510737058448e-003 -4.4156261792730848e-003
      -3.9141353401191603e-003 5.6342500712950995e-003
      -3.9262254982895088e-002 -3.9878768207315361e-002
      3.2062533273704036e-002 -3.9128644495217246e-002
      -5.2271796731174970e-002 6.8371595334561622e-002
      2.1376111466079151e-002 2.5623496932898837e-002
      -1.3981850503443853e-002 2.3097612000577954e-002
      2.9773867405758193e-002 -4.2550526253725532e-002
      6.0335590503430309e-003 3.4854981479112575e-003
      -3.2304190724083311e-003 -4.8390273875858715e-003
      1.0616477395845659e-002 -5.3325960204976619e-003
      -6.4508897640147443e-003 -9.9501250133745955e-003
      1.3416465167042051e-002 -8.1267157904719011e-003
      -2.1190058556228866e-002 2.0907026815705609e-002
      -9.4757191764422224e-004 -3.6002495713542571e-003
      6.6310913703029450e-003 1.8912987756827622e-003
      3.6481040520893230e-003 -2.0083492729461171e-003
      6.0849801036787403e-003 8.6873743583583945e-003
      9.1237962175153215e-004 8.4380607374594224e-003
      1.0392002027238367e-002 -1.9546040372887308e-002
      2.1954883315477840e-002 1.5027200062861134e-002
      -1.2042281101295035e-002 2.7852813124647081e-002
      2.5906145426556344e-002 -3.2100574798537389e-002
      2.4623110104731748e-002 1.0433807109570991e-002
      -4.2635627732729598e-003 1.1156895655543850e-002
      2.5768929483801700e-002 -3.3638734082970752e-002
      5.9408498718473302e-003 5.7034215760681005e-003
      5.1755394096340288e-003 1.1763198685774023e-002
      1.4295320110514797e-002 -2.1858552705603704e-002
      1.2980349726109577e-002 1.5267811110714142e-002
      -1.7796178570020731e-002 1.1980802649448492e-002
      3.2094418701219936e-002 -3.8242246021259835e-002
      -2.8417179496844636e-003 2.9590132721856463e-003
      -3.6152718254343053e-003 6.3796234203751081e-003
      6.7652727920385200e-003 -1.3307685137147333e-003
      6.8619020972336608e-003 -2.7973605098081376e-003
      -1.4276809682007292e-003 -2.4850978770574982e-003
      -1.8438937268741577e-003 -8.7550829213338070e-003
      2.8384976181644865e-002 1.7463459593342823e-002
      -1.2939791792259493e-002 2.2188840617926128e-002
      4.1762981527043719e-002 -6.3478779165051707e-002
      2.8770539064543462e-002 3.4474859689747110e-002
      -2.4373113250024232e-002 3.9314481386433828e-002
      4.0796700324846655e-002 -6.0170145700650525e-002
      -2.9036028741915187e-002 -2.2810714549351564e-002
      1.5822335198687355e-002 -3.0785792716314597e-002
      -3.4983825641935827e-002 5.6719304013777679e-002
      -3.9900329227987499e-003 -3.6120231755015195e-004
      8.9006529796754521e-003 -1.9074104989161679e-003
      -6.0589392794036601e-003 2.2684692134778316e-002
      2.8675449206178375e-002 1.2787870153001925e-002
      -1.7435711327332022e-002 2.0393769916811726e-002
      2.5838632035134371e-002 -3.8452479219835037e-002
      5.2132877602560929e-003 7.6356936710765752e-003
      -2.0691925458160816e-003 -6.6391417679129323e-004
      1.7280652641597138e-005 -1.4499014122429084e-002
      -2.9964583850069625e-002 -2.5665144641884973e-002
      2.1143482361947151e-002 -2.4372674891115890e-002
      -3.1971630292814933e-002 4.1041616587020886e-002
      -4.2322919349245806e-002 -3.9936653844601940e-002
      2.8654604988922919e-002 -3.6270989988895365e-002
      -5.6364083640095673e-002 7.0346626403168716e-002
      3.6715662749191801e-003 -2.9464841397678168e-003
      1.6862182542483699e-003 7.2101272257390336e-003
      6.4161189062316246e-003 -9.1793945511452011e-003
      -1.1713952637756006e-004 -1.2832869769948819e-003
      -4.5130847421194845e-003 2.2986884312888255e-003
      -1.0347188361521433e-002 1.6769360534284190e-002
      -1.1199534189315798e-002 -5.0917917103197891e-003
      -1.0950483213974505e-003 -7.6301369013551416e-003
      -1.1867728343046478e-002 1.1784627113397497e-002
      -8.8609355014795874e-003 -9.0295584676631513e-003
      9.6420627074302323e-003 -6.0541236573562725e-003
      -1.5266613075802302e-002 1.8508719190723253e-002
      -5.5943509313857824e-003 6.5152518147579431e-003
      -1.7691827089746722e-003 3.6290275462305390e-003
      -1.3897127824919205e-004 5.2845826381959686e-003
      -9.5609808547106167e-003 -6.4038341866922543e-003
      1.0411732628594949e-002 -9.4775815335527251e-003
      -2.0777022459906522e-002 3.2021150196997181e-002
      1.9411875529500792e-002 1.1249348645939612e-002
      -1.5373960070753094e-003 1.9842796345286517e-002
      1.4759217084147205e-002 -2.4343150710951805e-002
      3.9665780836525208e-003 9.4767428485138701e-003
      -3.5587298752488934e-003 -2.8046567184540328e-003
      7.4550630055617592e-004 -3.8800133375916646e-003
      -2.2714202545780625e-002 -8.1593981517765254e-003
      1.1425205186572059e-002 -1.0221360759241195e-002
      -1.6768797893684923e-002 2.0415231991774162e-002
      -9.2643493879650772e-004 1.1644862100114060e-002
      -7.1200809203644040e-004 1.2209297122972336e-002
      2.6645788966114057e-003 -2.4993747198801734e-004
      1.9913999463216654e-002 2.6637126735774481e-003
      -6.1320423545794724e-003 5.2048056546375619e-003
      1.6461276316176655e-002 -2.8232308980362809e-002
      2.2143485362644641e-002 2.1463792529990870e-002
      -1.5784670605993305e-002 2.1805401069250843e-002
      1.1958979101414352e-002 -1.8046176307401383e-002
      -8.2619890858232539e-003 -7.0710186278125226e-003
      1.0189781626684642e-002 -5.3119265016283203e-003
      -1.5484658320077810e-002 1.3961890003802909e-002
      -5.2255732093474595e-002 -4.8011264645776715e-002
      3.8068651349783905e-002 -5.5115140765131930e-002
      -5.9026093972168112e-002 8.7146354978595131e-002
      -3.9426593323619186e-003 -1.4200670750659321e-003
      7.3755694341139403e-004 -4.2407078020623547e-004
      -4.1410332105720838e-003 1.7023031162481304e-002
      1.7810570833543069e-002 1.7646724139171718e-002
      -1.7105461312235781e-002 1.6189708060146444e-002
      1.5679137332070967e-002 -8.1224316376125715e-003
      1.2483069349080682e-002 6.1971250798651505e-003
      -8.2861614674857621e-003 9.7426451904804347e-003
      6.3948359904111973e-003 -1.6333054994654612e-002
      -8.6282421935237694e-003 -9.9517953265747788e-003
      -4.0572437836617157e-003 -3.0340998807375993e-003
      -1.2737316910851939e-002 7.9436830557721109e-003
      1.2103173433993027e-002 -1.9934639679629134e-003
      -3.1039586178408917e-004 -1.2995434967874258e-004
      4.2095875281314621e-003 -1.6273021567270191e-002
      -2.5674651338584098e-002 -2.1226451043888379e-002
      1.3209330596393029e-002 -2.1912276083598491e-002
      -2.7597427553024884e-002 5.5734881427103485e-002
      3.2539648918068903e-002 3.1876163976282949e-002
      -2.0600902999459339e-002 2.8193211130536969e-002
      3.8286009053296668e-002 -6.0892722506776360e-002
      -3.7943806843606541e-003 -4.7412652109111537e-003
      -2.2772254556117978e-003 -2.4131282534009826e-003
      -2.9656572644339184e-003 5.3115707539335508e-003
      -8.3494280263034740e-003 -1.2076441826611702e-003
      5.3688530855571081e-003 -5.6805580667461408e-004
      -5.3573502211253857e-003 1.5112258738630615e-002
      -6.0225058894305024e-003 -1.5104538275572802e-003
      1.0842844665127870e-003 1.1722276119662868e-003
      -5.7262879998536626e-003 1.1621567218209465e-002
      2.6469648418488999e-002 1.9273999412741608e-002
      -1.5056244102486443e-002 2.3543944138761558e-002
      2.7651926692012611e-002 -4.0303976515460027e-002
      7.2774125639920063e-003 9.1891480905329000e-003
      -6.4156843278510029e-003 5.8042052661165617e-003
      1.1309070567764168e-002 -1.4127397150815664e-002
      4.0051090869471333e-002 3.6414280716838290e-002
      -2.4916152242032075e-002 4.7376165670255550e-002
      5.4898520679261292e-002 -8.2863001319931573e-002
      1.3575510601747404e-003 -6.2251453773333300e-003
      1.5220978511529502e-003 1.5304121769384340e-003
      4.6607587509621936e-003 5.0302475814922292e-003
      1.3203274534462876e-002 8.0285229281502641e-004
      -7.9853007569176421e-003 8.0563915271040665e-003
      1.3951606399711559e-002 -1.3716832070775406e-002
      1.0229939165276161e-002 4.2946823365839511e-004
      -1.0331783584742021e-002 1.3315108197195049e-002
      1.5211446328798690e-002 -1.4138245085115610e-002
      -6.1530901496207845e-003 2.1093879473133266e-003
      1.1812265298071398e-003 -5.7122775928512845e-003
      5.9474427353545106e-003 -9.1149190993622380e-003
      1.8680900047552240e-002 1.4860125349535234e-002
      -1.5327278846532255e-002 1.7089856150769606e-002
      1.8162741082165670e-002 -2.3888634957952921e-002
      -1.0363919755931584e-002 -7.8420846488652281e-003
      1.0851504221890277e-002 -2.0222783497951605e-003
      -9.1840777423804008e-003 1.1626403277540484e-002
      -1.2527736872309066e-002 -1.0892676802559899e-002
      -1.1385320581935080e-003 -2.5768990416715014e-003
      -3.3623537505697702e-003 1.1772888824039301e-002
      1.7689256929811499e-002 1.5815200089020025e-002
      -9.5143579860112633e-003 6.5512722094677430e-003
      1.7709394537954247e-002 -3.4737034402808800e-002
      -1.6084633408008940e-002 -1.8890301205114438e-002
      1.4215182432416946e-002 -2.0878048036202263e-002
      -2.9234512318573706e-002 4.2843348742030517e-002
      1.1313257625851907e-002 6.3626419452578404e-004
      -1.7641030262267794e-003 9.0736201116451277e-004
      1.0982291084571941e-002 -6.6948664513315779e-004
      -2.1413523022776298e-002 -1.4458917847657606e-002
      1.5444585302900816e-002 -2.9619509517560885e-002
      -3.1504909121896615e-002 4.4884465504037886e-002
      1.6442018162619938e-002 1.9779396556714696e-002
      -1.2718038956199051e-002 1.7219799719322866e-002
      2.9216906909887801e-002 -2.4371048224740677e-002
      -1.6147070684779611e-002 -2.1071827395953376e-002
      1.8154179712939311e-002 -1.6665495391703613e-002
      -3.0205734082721196e-002 3.4494326309417872e-002
      -2.5188421630665948e-003 -1.1747215494257047e-002
      1.1090052999146518e-004 -1.2493372529396616e-002
      -5.8452996191433355e-003 -7.2032377815969845e-003
      2.4989086674986009e-002 1.6285920401805428e-002
      -3.5817096155923945e-003 1.3360014149089381e-002
      1.4194537028625283e-002 -2.8331252544919073e-002
      -2.2282640468352754e-003 -5.3104591853026552e-003
      2.2482024679064366e-003 -4.2385792929408453e-003
      -2.5833523033229546e-003 -4.1141434915344215e-003
      1.2944995854840763e-002 9.1914832572447033e-003
      -1.0579359960110724e-002 1.3567847808036399e-002
      1.5941997690680023e-002 -3.5554382829670383e-002
      -1.4504042095783435e-002 -1.1830185127069423e-002
      9.7820927088946158e-003 -1.0944574832586896e-002
      -1.2368830873769866e-002 1.8835656075098493e-002
      2.0726370778539624e-003 -2.1722065448433843e-003
      -4.5844040612389395e-003 6.8825578806762464e-003
      2.0312195167968869e-003 3.6032553622235731e-004
      1.3903129106472052e-002 1.1777839952003677e-002
      -8.9994741726647128e-003 1.8712310097329023e-002
      2.7903018835261261e-002 -3.8747410060197635e-002
      3.4980007925480235e-002 1.7913398151169168e-002
      -1.2196163887732765e-002 2.5362916730311470e-002
      2.9474235671811969e-002 -3.8665205036612436e-002
      -2.1276821207535240e-002 -2.1050812240111665e-002
      1.3018313788106662e-002 -1.6594421406031411e-002
      -1.9047293347097396e-002 2.2066105207011567e-002
      8.9141893171061637e-003 1.1989053486218013e-002
      -1.5692248824644159e-003 5.0402357127697743e-003
      1.2896634387668908e-002 -2.3026189771317023e-002
      -6.9872688473937553e-005 -1.3017770945813321e-002
      9.9375645264608431e-003 1.0525322300443715e-003
      -6.5188619048026268e-003 -1.9522326626493229e-003
      -9.8882460722969703e-003 -9.2527008641745279e-003
      -4.9112350025798139e-003 -4.3910801247387535e-003
      -8.3361434125542189e-003 1.4116770885891474e-002
      -1.9610324519204632e-004 -3.4333554965124808e-003
      -3.0522779506198063e-003 -4.4527104644404909e-004
      -8.2861400390370991e-004 -3.4679396939066944e-003
      6.3672881150466064e-003 -1.3191659229067534e-003
      -8.3242728903888685e-004 1.2984062589058735e-002
      1.1275325327746236e-002 -4.8860936404573384e-003
      8.6602035444559942e-003 4.3051658061724800e-003
      1.5236557355222829e-003 5.6320753510023715e-003
      2.3344768566024238e-003 -1.1491579562992115e-002
      2.7028032344175900e-002 1.9072238070870103e-002
      -1.3973013388570826e-002 2.4323998782096207e-002
      2.4531255548878982e-002 -2.6791341740057067e-002
      1.0308301813549140e-002 1.1286299033773465e-002
      -2.9738388520466875e-003 2.0073055656718276e-002
      2.2195936024896973e-002 -2.3217437388378798e-002
      -1.6837624606417318e-002 -7.6223725695030167e-004
      1.8048142643333168e-003 -1.3708159202756254e-002
      -8.1724386106785309e-003 2.3007488811166120e-002
      -2.9845764279383815e-002 -2.7506434550204840e-002
      1.0390268288259301e-002 -2.7054704563229563e-002
      -2.7437848549974164e-002 5.3541987847316785e-002
      -1.8896536565861429e-002 -1.6652533574779624e-002
      5.4627595619026227e-003 -5.7612168209741329e-003
      -1.8717099901441828e-002 3.7184022577766811e-002
      -2.5543983991223426e-002 -2.5339372753359134e-002
      9.7102176474577230e-003 -2.3129373026261984e-002
      -1.9166542424825544e-002 3.3207701257767064e-002
      1.2020836741531413e-002 7.0004731844277943e-003
      -1.2436499907788095e-002 1.3092303070019641e-002
      5.9971572768892324e-003 -2.0578699052872077e-002
      -5.7425066383678632e-004 -6.5852192077797368e-003
      -2.7735909050719400e-003 2.4459832624796729e-004
      5.6257353865371666e-003 -9.6922566669571176e-004
      4.6948542558218967e-003 -2.0421212277259094e-003
      -7.5173910568670536e-003 4.1711448257606525e-003
      2.9188764806918478e-003 -5.8814432859984203e-003
      1.8034232481446213e-002 1.1566267611957299e-002
      -9.6877174383695579e-003 7.2966987700120549e-003
      8.7058633707559185e-003 -1.3717976756058192e-002
      1.6020158797090230e-002 1.4109486075570320e-002
      -7.1473795473748093e-003 4.9697611679071288e-003
      6.6585863291409291e-003 -1.5894510765450388e-002
      4.7839900156221946e-003 -8.4236513954399732e-004
      -9.0729777781517178e-003 -1.5262163057625008e-003
      1.2292913349949863e-002 -1.0456502143302926e-002
      -2.7578219598748708e-002 -1.0505744407775823e-002
      1.7068759387789741e-002 -2.3511331717980487e-002
      -2.6972870671298069e-002 3.3545081493879331e-002
      4.0354337158829178e-003 9.9599084983704490e-003
      -5.7479796208632257e-003 4.3711326216721302e-003
      1.1980753607198000e-002 -7.8156259621947836e-003
      3.2887837512348916e-002 2.4288665852868829e-002
      -2.5135659955658390e-002 3.2927882071314522e-002
      2.5444209341564886e-002 -4.1880591668679343e-002
      1.8136744138502569e-003 9.4876374581623693e-003
      1.0773319414079110e-003 4.3014257010860514e-003
      5.2065649490978718e-003 -1.5697743861103088e-002
      1.2887082426068654e-002 1.4197017424220040e-002
      -4.6686429592014090e-003 1.5888047010433479e-002
      1.2181126210021131e-002 -1.4286958956159678e-002
      -1.5027219652728566e-001 -1.0629875272143313e-001
      8.8497635326038396e-002 -1.3407643849428960e-001
      -1.5587852891598955e-001 2.1406104354268865e-001</_>
    <_>
      5.2404259844302559e-001 4.1528226403807400e-001
      -3.1136282790388992e-001 4.9098615559598274e-001
      5.9172526242232615e-001 -8.7508308239742749e-001
      -1.5100850835534782e-001</_></weights></opencv_ml_ann_mlp>
</opencv_storage>
